Metadata-Version: 2.1
Name: test-package-joao-araguari
Version: 0.0.2
Summary: A package to make integrals in parallel
Author: God, the one who wrote everything
